UFSHMessages/__init__.py
UFSHMessages/config.py
UFSHMessages/message.py
UFSHMessages/schema.py
UFSHMessages-0.0.2.dist-info/LICENSE
UFSHMessages-0.0.2.dist-info/METADATA
UFSHMessages-0.0.2.dist-info/WHEEL
UFSHMessages-0.0.2.dist-info/top_level.txt
UFSHMessages-0.0.2.dist-info/RECORD
