Metadata-Version: 2.1
Name: UFSHMessages
Version: 0.0.2
Summary: Package for parsing and packing UFSH messages
Home-page: https://github.com/UFSH/messages-python
Author: Alexander Hansen
Author-email: alexander@thenorwegian.dev
License: UNKNOWN
Project-URL: Bug Tracker, https://github.com/UFSH/messages-python/issues
Platform: UNKNOWN
Classifier: Programming Language :: Python :: 3
Classifier: License :: OSI Approved :: MIT License
Classifier: Operating System :: OS Independent
Requires-Python: >=3.6
License-File: LICENSE
